smollm/__about__.py
smollm/__init__.py
smollm-0.0.1.dist-info/METADATA
smollm-0.0.1.dist-info/WHEEL
smollm-0.0.1.dist-info/licenses/LICENSE.txt
smollm-0.0.1.dist-info/RECORD
